uniqcalc/__init__.py
uniqcalc-0.1.2.dist-info/LICENSE
uniqcalc-0.1.2.dist-info/METADATA
uniqcalc-0.1.2.dist-info/WHEEL
uniqcalc-0.1.2.dist-info/top_level.txt
uniqcalc-0.1.2.dist-info/RECORD
