Metadata-Version: 2.1
Name: uniqcalc
Version: 0.1.2
Summary: This Package will help you calculate quickly
Home-page: https://github.com/somasekharreddy-921/uniqcalc
Author: somasekhar
Author-email: somu.bommaka@gmail.com
License: UNKNOWN
Project-URL: Bug Tracker, https://github.com/somasekharreddy-921/uniqcalc/issues
Platform: UNKNOWN
Classifier: Programming Language :: Python :: 3
Classifier: License :: OSI Approved :: MIT License
Classifier: Operating System :: OS Independent
Requires-Python: >=3.6
License-File: LICENSE
